session_dev/__init__.py
session_dev/cli.py
session_dev/core/__init__.py
session_dev/core/initializer.py
session_dev/core/manager.py
session_dev/core/models.py
session_dev/core/work_items.py
session_dev/scripts/__init__.py
session_dev/scripts/curate_learnings.py
session_dev/scripts/generate_stack.py
session_dev/scripts/generate_tree.py
session_dev/scripts/session_complete.py
session_dev/scripts/session_init.py
session_dev/scripts/session_validate.py
session_dev/templates/__init__.py
session_dev/utils/__init__.py
session_dev/utils/file_ops.py
session_dev/utils/git_ops.py
session_dev-0.1.0.dist-info/licenses/LICENSE
session_dev-0.1.0.dist-info/METADATA
session_dev-0.1.0.dist-info/WHEEL
session_dev-0.1.0.dist-info/entry_points.txt
session_dev-0.1.0.dist-info/top_level.txt
session_dev-0.1.0.dist-info/RECORD
