Metadata-Version: 2.4
Name: session-dev
Version: 0.1.0
Summary: Session-Driven Development: A framework for AI-augmented software development with perfect context continuity
Author-email: Session-Dev Project <noreply@session-dev.io>
License-Expression: MIT
Project-URL: Homepage, https://github.com/session-dev/session-dev
Project-URL: Documentation, https://session-dev.readthedocs.io
Project-URL: Repository, https://github.com/session-dev/session-dev
Project-URL: Issues, https://github.com/session-dev/session-dev/issues
Keywords: ai,development,automation,claude,workflow,productivity
Classifier: Development Status :: 3 - Alpha
Classifier: Intended Audience :: Developers
Classifier: Programming Language :: Python :: 3
Classifier: Programming Language :: Python :: 3.9
Classifier: Programming Language :: Python :: 3.10
Classifier: Programming Language :: Python :: 3.11
Classifier: Programming Language :: Python :: 3.12
Classifier: Topic :: Software Development
Classifier: Topic :: Software Development :: Libraries :: Python Modules
Requires-Python: >=3.9
License-File: LICENSE
Requires-Dist: click>=8.1.0
Requires-Dist: pydantic>=2.0.0
Requires-Dist: rich>=13.0.0
Requires-Dist: pyyaml>=6.0
Requires-Dist: gitpython>=3.1.0
Requires-Dist: jinja2>=3.1.0
Requires-Dist: toml>=0.10.0
Provides-Extra: dev
Requires-Dist: pytest>=7.4.0; extra == "dev"
Requires-Dist: pytest-cov>=4.1.0; extra == "dev"
Requires-Dist: black>=23.0.0; extra == "dev"
Requires-Dist: ruff>=0.1.0; extra == "dev"
Requires-Dist: mypy>=1.5.0; extra == "dev"
Requires-Dist: pre-commit>=3.0.0; extra == "dev"
Dynamic: license-file
